[{
			"id": 65,
			"brandId": 12,
			"logo": "http://pic.tuanche.com/car/20151225/14510331696396134_s.jpg",
			"styleName": "思域",
			"factoryPrice": "指导价:12.18-19.98万",
			"content": "已有37人报名",
			"isBuy": 0,
			"manNum": 37,
			"isNew": 0,
			"prefix": "已有",
			"suffix": "人报名",
			"levelStr": "1.8L 2.4L",
			"brandName": "东风本田",
			"firmBrandId": 0,
			"identify": 1
		}, {
			"id": 64,
			"brandId": 12,
			"logo": "http://pic.tuanche.com/car/20151009/14443523111362854_s.jpg",
			"styleName": "本田CR-V",
			"factoryPrice": "指导价:17.98-24.98万",
			"content": "已有131人报名",
			"isBuy": 0,
			"manNum": 131,
			"isNew": 0,
			"prefix": "已有",
			"suffix": "人报名",
			"levelStr": "2.0L 2.4L",
			"brandName": "东风本田",
			"firmBrandId": 0,
			"identify": 1
		}, {
			"id": 51,
			"brandId": 9,
			"logo": "http://pic.tuanche.com/car/20150812/14393750925112300_s.jpg",
			"styleName": "君威",
			"factoryPrice": "指导价:17.89-27.99万",
			"content": "已有60人报名",
			"isBuy": 0,
			"manNum": 60,
			"isNew": 0,
			"prefix": "已有",
			"suffix": "人报名",
			"levelStr": "1.6T 2.0L 2.0T",
			"brandName": "通用别克",
			"firmBrandId": 0,
			"identify": 1
		}, {
			"id": 49,
			"brandId": 9,
			"logo": "http://pic.tuanche.com/car/20150924/14430852230783071_s.jpg",
			"styleName": "英朗",
			"factoryPrice": "指导价:10.99-18.15万",
			"content": "已有63人报名",
			"isBuy": 0,
			"manNum": 63,
			"isNew": 0,
			"prefix": "已有",
			"suffix": "人报名",
			"levelStr": "1.4T 1.5L 1.6L 1.6T 1.8L",
			"brandName": "通用别克",
			"firmBrandId": 0,
			"identify": 1
		}, {
			"id": 4481,
			"brandId": 2,
			"logo": "http://pic.tuanche.com/car/20150805/1438762751768534_s.jpg",
			"styleName": "朗行",
			"factoryPrice": "指导价:11.29-16.39万",
			"content": "已有25人报名",
			"isBuy": 0,
			"manNum": 25,
			"isNew": 0,
			"prefix": "已有",
			"suffix": "人报名",
			"levelStr": "1.4T 1.6L",
			"brandName": "上海大众",
			"firmBrandId": 0,
			"identify": 1
		}, {
			"id": 36,
			"brandId": 6,
			"logo": "http://pic.tuanche.com/car/20151012/1444612315282307_s.jpg",
			"styleName": "福克斯",
			"factoryPrice": "指导价:9.98-16.99万",
			"content": "已有106人报名",
			"isBuy": 0,
			"manNum": 106,
			"isNew": 0,
			"prefix": "已有",
			"suffix": "人报名",
			"levelStr": "1.0T 1.5T 1.6L 1.8L 2.0L",
			"brandName": "长安福特",
			"firmBrandId": 0,
			"identify": 1
		}, {
			"id": 279,
			"brandId": 8,
			"logo": "http://pic.tuanche.com/car/20151009/14443588044719018_s.jpg",
			"styleName": "标致508",
			"factoryPrice": "指导价:17.37-26.97万",
			"content": "已有24人报名",
			"isBuy": 0,
			"manNum": 24,
			"isNew": 0,
			"prefix": "已有",
			"suffix": "人报名",
			"levelStr": "1.6T 1.8T 2.0L",
			"brandName": "东风标致",
			"firmBrandId": 0,
			"identify": 1
		}, {
			"id": 274,
			"brandId": 21,
			"logo": "http://pic.tuanche.com/car/20151225/14510303502721696_s.jpg",
			"styleName": "起亚K5",
			"factoryPrice": "指导价:15.98-24.98万",
			"content": "已有36人报名",
			"isBuy": 0,
			"manNum": 36,
			"isNew": 0,
			"prefix": "已有",
			"suffix": "人报名",
			"levelStr": "1.6T 2.0L 2.0T",
			"brandName": "东风悦达起亚",
			"firmBrandId": 0,
			"identify": 1
		}, {
			"id": 2,
			"brandId": 1,
			"logo": "http://pic.tuanche.com/car/20150930/14435908384389854_s.jpg",
			"styleName": "高尔夫",
			"factoryPrice": "指导价:12.19-23.99万",
			"content": "已有102人报名",
			"isBuy": 0,
			"manNum": 102,
			"isNew": 0,
			"prefix": "已有",
			"suffix": "人报名",
			"levelStr": "1.2T 1.4T 1.6L 2.0T",
			"brandName": "一汽-大众",
			"firmBrandId": 0,
			"identify": 1
		}, {
			"id": 11,
			"brandId": 2,
			"logo": "http://pic.tuanche.com/car/20151106/14468007816977266_s.jpg",
			"styleName": "Polo",
			"factoryPrice": "指导价:7.59-15.89万",
			"content": "已有75人报名",
			"isBuy": 0,
			"manNum": 75,
			"isNew": 0,
			"prefix": "已有",
			"suffix": "人报名",
			"levelStr": "1.4L 1.4T 1.6L",
			"brandName": "上海大众",
			"firmBrandId": 0,
			"identify": 1
		}, {
			"id": 1,
			"brandId": 1,
			"logo": "http://pic.tuanche.com/car/20151022/14454758762412870_s.jpg",
			"styleName": "一汽-大众CC",
			"factoryPrice": "指导价:25.28-34.28万",
			"content": "已有23人报名",
			"isBuy": 0,
			"manNum": 23,
			"isNew": 0,
			"prefix": "已有",
			"suffix": "人报名",
			"levelStr": "1.8T 2.0T 3.0L",
			"brandName": "一汽-大众",
			"firmBrandId": 0,
			"identify": 1
		}]